amulet/__init__.py
amulet/attribute_inference/__init__.py
amulet/attribute_inference/attacks/__init__.py
amulet/attribute_inference/attacks/attribute_inference_attack.py
amulet/attribute_inference/attacks/duddu_cikm_2022.py
amulet/attribute_inference/metrics/__init__.py
amulet/attribute_inference/metrics/attack_accuracy.py
amulet/data_reconstruction/__init__.py
amulet/data_reconstruction/attacks/__init__.py
amulet/data_reconstruction/attacks/data_reconstruction_attack.py
amulet/data_reconstruction/attacks/fredrikson_ccs_2015.py
amulet/data_reconstruction/metrics/__init__.py
amulet/data_reconstruction/metrics/similarity_evaluation.py
amulet/datasets/__data.py
amulet/datasets/__image_datasets.py
amulet/datasets/__init__.py
amulet/datasets/__tabular_datasets.py
amulet/discriminatory_behavior/__init__.py
amulet/discriminatory_behavior/defenses/__init__.py
amulet/discriminatory_behavior/defenses/adversarial_debiasing.py
amulet/discriminatory_behavior/defenses/discr_behavior_defense.py
amulet/discriminatory_behavior/metrics/__init__.py
amulet/discriminatory_behavior/metrics/discriminatory_behavior.py
amulet/distribution_inference/__init__.py
amulet/distribution_inference/attacks/__init__.py
amulet/distribution_inference/attacks/distribution_inference.py
amulet/evasion/__init__.py
amulet/evasion/attacks/__init__.py
amulet/evasion/attacks/evasion_attack.py
amulet/evasion/attacks/projected_gradient_descent.py
amulet/evasion/defenses/__init__.py
amulet/evasion/defenses/evasion_defense.py
amulet/evasion/defenses/projected_gradient_descent.py
amulet/membership_inference/__init__.py
amulet/membership_inference/attacks/__init__.py
amulet/membership_inference/attacks/lira.py
amulet/membership_inference/attacks/membership_inference_attack.py
amulet/membership_inference/defenses/__init__.py
amulet/membership_inference/defenses/dp_sgd.py
amulet/membership_inference/defenses/membership_inference_defense.py
amulet/membership_inference/metrics/__init__.py
amuletml-0.5.0.dist-info/LICENSE
amuletml-0.5.0.dist-info/METADATA
amuletml-0.5.0.dist-info/WHEEL
amuletml-0.5.0.dist-info/RECORD
