Metadata-Version: 2.1
Name: amuletml
Version: 0.5.0
Summary: Amulet is a Python machine learning (ML) package to evaluate the susceptibility of different risks to security, privacy, and fairness.
License: Apache-2.0
Author: Asim Waheed
Author-email: asim.waheed29@gmail.com
Requires-Python: >=3.11,<4.0
Classifier: License :: OSI Approved :: Apache Software License
Classifier: Programming Language :: Python :: 3
Classifier: Programming Language :: Python :: 3.11
Classifier: Programming Language :: Python :: 3.12
Classifier: Programming Language :: Python :: 3.13
Requires-Dist: captum (==0.7.0)
Requires-Dist: cleverhans (==4.0.0)
Requires-Dist: gdown (==5.2.0)
Requires-Dist: matplotlib (==3.8.3)
Requires-Dist: numpy (==1.26.4)
Requires-Dist: opacus (==1.4.1)
Requires-Dist: pandas (==2.2.1)
Requires-Dist: scikit-image (==0.25.1)
Requires-Dist: scikit-learn (==1.4.1.post1)
Requires-Dist: scipy (==1.12.0)
Requires-Dist: torch (>=2.2.0,<3.0.0)
Requires-Dist: torchvision (>=0.18.0,<0.19.0)
Requires-Dist: tqdm (==4.66.2)
Requires-Dist: ucimlrepo (==0.0.3)
Requires-Dist: wget (==3.2.0)
